wumpy/client/__init__.py
wumpy_client-0.0.0.dist-info/LICENSE
wumpy_client-0.0.0.dist-info/WHEEL
wumpy_client-0.0.0.dist-info/METADATA
wumpy_client-0.0.0.dist-info/RECORD
